staffspy/__init__.py
staffspy/linkedin/certifications.py
staffspy/linkedin/comments.py
staffspy/linkedin/employee.py
staffspy/linkedin/employee_bio.py
staffspy/linkedin/experiences.py
staffspy/linkedin/languages.py
staffspy/linkedin/linkedin.py
staffspy/linkedin/schools.py
staffspy/linkedin/skills.py
staffspy/solvers/capsolver.py
staffspy/solvers/solver.py
staffspy/solvers/solver_type.py
staffspy/solvers/two_captcha.py
staffspy/utils/driver_type.py
staffspy/utils/exceptions.py
staffspy/utils/models.py
staffspy/utils/utils.py
staffspy-0.2.24.dist-info/LICENSE
staffspy-0.2.24.dist-info/METADATA
staffspy-0.2.24.dist-info/WHEEL
staffspy-0.2.24.dist-info/RECORD
