Metadata-Version: 2.1
Name: staffspy
Version: 0.2.24
Summary: Staff scraper library for LinkedIn
Author: Cullen Watson
Author-email: cullen@bunsly.com
Requires-Python: >=3.10,<4.0
Classifier: Programming Language :: Python :: 3
Classifier: Programming Language :: Python :: 3.10
Classifier: Programming Language :: Python :: 3.11
Classifier: Programming Language :: Python :: 3.12
Classifier: Programming Language :: Python :: 3.13
Provides-Extra: browser
Requires-Dist: 2captcha-python (>=1.2.8,<2.0.0)
Requires-Dist: beautifulsoup4 (>=4.12.3,<5.0.0)
Requires-Dist: pandas (>=2.2.2,<3.0.0)
Requires-Dist: pydantic (>=2.7.2,<3.0.0)
Requires-Dist: python-dateutil (>=2.9.0.post0,<3.0.0)
Requires-Dist: requests (>=2.32.3,<3.0.0)
Requires-Dist: selenium (>=4.3.0,<5.0.0) ; extra == "browser"
Requires-Dist: tenacity (>=8.5.0,<9.0.0)
Requires-Dist: tldextract (>=5.1.2,<6.0.0)
